{"happy": [0.8, 0.5], "sad": [-0.8, 0.2], "bread": [0.3, 0.1], "warm": [0.6, 0.3], "fire": [0.1, 0.8], "friend": [0.7, 0.3], "laughs": [0.8, 0.6], "home": [0.9, 0.1], "safe": [0.8, 0.1], "bright": [0.6, 0.4], "together": [0.7, 0.2], "cold": [-0.5, 0.4], "road": [0.0, 0.1], "threat": [-0.8, 0.9], "danger": [-0.9, 0.9], "follows": [-0.1, 0.5], "closer": [0.0, 0.6], "screams": [-0.9, 0.9], "blood": [-0.8, 0.8], "fight": [-0.7, 0.9], "run": [-0.2, 0.8], "enemy": [-0.8, 0.7], "attacks": [-0.9, 0.9], "death": [-1.0, 0.9], "terror": [-1.0, 1.0], "rage": [-0.8, 0.9], "light": [0.5, 0.3], "last": [0.1, 0.1], "peace": [0.9, 0.0], "relief": [0.8, 0.1]}
